[{"id":2124,"num":"U1A","dest":"North Stoneham","uri":"http:\/\/id.southampton.ac.uk\/bus-route\/2124","url":"\/bus-route\/2124.html"},{"id":2125,"num":"U1C","dest":"Southampton City Centre, Docks (Soton)","uri":"http:\/\/id.southampton.ac.uk\/bus-route\/2125","url":"\/bus-route\/2125.html"},{"id":2126,"num":"U1E","dest":"Eastleigh (Hants)","uri":"http:\/\/id.southampton.ac.uk\/bus-route\/2126","url":"\/bus-route\/2126.html"},{"id":2127,"num":"U1w","dest":"Swaythling","uri":"http:\/\/id.southampton.ac.uk\/bus-route\/2127","url":"\/bus-route\/2127.html"},{"id":2128,"num":"U2B","dest":"Bassett Green","uri":"http:\/\/id.southampton.ac.uk\/bus-route\/2128","url":"\/bus-route\/2128.html"},{"id":2129,"num":"U2C","dest":"Southampton City Centre","uri":"http:\/\/id.southampton.ac.uk\/bus-route\/2129","url":"\/bus-route\/2129.html"},{"id":2130,"num":"U6","dest":"Bassett","uri":"http:\/\/id.southampton.ac.uk\/bus-route\/2130","url":"\/bus-route\/2130.html"},{"id":2131,"num":"U6C","dest":"Southampton City Centre, Docks (Soton)","uri":"http:\/\/id.southampton.ac.uk\/bus-route\/2131","url":"\/bus-route\/2131.html"},{"id":2132,"num":"U6H","dest":"Highfield (Soton), Shirley Warren","uri":"http:\/\/id.southampton.ac.uk\/bus-route\/2132","url":"\/bus-route\/2132.html"},{"id":2133,"num":"U9","dest":"Shirley Warren, Midanbury","uri":"http:\/\/id.southampton.ac.uk\/bus-route\/2133","url":"\/bus-route\/2133.html"},{"id":2134,"num":"U9","dest":"Midanbury, Shirley Warren","uri":"http:\/\/id.southampton.ac.uk\/bus-route\/2134","url":"\/bus-route\/2134.html"}]